indxdatalaketools/DataLakeGlobals.py
indxdatalaketools/Helpers.py
indxdatalaketools/__init__.py
indxdatalaketools/ArgumentValidation/Argument.py
indxdatalaketools/ArgumentValidation/ClientId.py
indxdatalaketools/ArgumentValidation/FileMetadata.py
indxdatalaketools/ArgumentValidation/PatientData.py
indxdatalaketools/ArgumentValidation/ValidationHelpers.py
indxdatalaketools/ArgumentValidation/__init__.py
indxdatalaketools/ClientCommands/DataLakeToolsClient.py
indxdatalaketools/ClientCommands/__init__.py
indxdatalaketools/ClientTools/ClientOps.py
indxdatalaketools/ClientTools/__init__.py
indxdatalaketools/ClientTools/Changelog/Insert.py
indxdatalaketools/ClientTools/Changelog/__init__.py
indxdatalaketools/ClientTools/Files/Upload.py
indxdatalaketools/ClientTools/Files/__init__.py
indxdatalaketools/ClientTools/PatientsTable/Insert.py
indxdatalaketools/ClientTools/PatientsTable/Update.py
indxdatalaketools/ClientTools/PatientsTable/__init__.py
indxdatalaketools/DataStandardizer/FileMetadata.py
indxdatalaketools/DataStandardizer/PatientTable.py
indxdatalaketools/DataStandardizer/__init__.py
indxdatalaketools/DocumentClassifierApi/DocumentClassifierApi.py
indxdatalaketools/DocumentClassifierApi/__init__.py
indxdatalaketools/GoogleClientWrappers/BigQuery.py
indxdatalaketools/GoogleClientWrappers/CloudStorage.py
indxdatalaketools/GoogleClientWrappers/CloudTasks.py
indxdatalaketools/GoogleClientWrappers/ComputeEngine.py
indxdatalaketools/GoogleClientWrappers/Scheduler.py
indxdatalaketools/GoogleClientWrappers/SecretManager.py
indxdatalaketools/GoogleClientWrappers/__init__.py
indxdatalaketools/GoogleClients/GoogleClients.py
indxdatalaketools/GoogleClients/__init__.py
indxdatalaketools/PatientsHoldingApi/HoldingTable.py
indxdatalaketools/PatientsHoldingApi/__init__.py
indxdatalaketools/PropertiesDBApi/Properties.py
indxdatalaketools/PropertiesDBApi/PropertiesApi.py
indxdatalaketools/PropertiesDBApi/__init__.py
indxdatalaketools-1.3.2.data/data/man/man1/DataLakeTools.1
indxdatalaketools-1.3.2.dist-info/LICENSE
indxdatalaketools-1.3.2.dist-info/METADATA
indxdatalaketools-1.3.2.dist-info/NOTICE
indxdatalaketools-1.3.2.dist-info/NOTICE-numpy
indxdatalaketools-1.3.2.dist-info/NOTICE-opencv-python.txt
indxdatalaketools-1.3.2.dist-info/NOTICE-requests.txt
indxdatalaketools-1.3.2.dist-info/WHEEL
indxdatalaketools-1.3.2.dist-info/entry_points.txt
indxdatalaketools-1.3.2.dist-info/top_level.txt
indxdatalaketools-1.3.2.dist-info/RECORD
