Metadata-Version: 2.1
Name: indxdatalaketools
Version: 1.3.2
Summary: Package that allows the upload of files to a datalake
Home-page: https://github.com/IntelligentDX-LLC/data-lake-tools
Author: Ryan McDermott
Author-email: rmcdermott@intelligentdx.com
License: Creative Commons Attribution-NonCommercial-NoDerivatives 4.0
Project-URL: Bug Tracker, https://github.com/IntelligentDX-LLC/data-lake-tools/issues
Classifier: Programming Language :: Python :: 3
Classifier: Operating System :: OS Independent
Requires-Python: >=3.8
License-File: LICENSE
License-File: NOTICE
License-File: NOTICE-numpy
License-File: NOTICE-opencv-python.txt
License-File: NOTICE-requests.txt
Requires-Dist: google-cloud-datastore (==2.5.1)
Requires-Dist: google-cloud-storage (==2.3.0)
Requires-Dist: google-cloud-bigquery (==3.1.0)
Requires-Dist: google-cloud-bigquery-storage (==2.13.1)
Requires-Dist: google-auth (==1.35.0)
Requires-Dist: google-cloud-pubsub (==2.12.1)
Requires-Dist: google-cloud-scheduler (==2.6.3)
Requires-Dist: google-cloud-secret-manager (==2.10.0)
Requires-Dist: google-cloud-logging (==2.7.0)
Requires-Dist: google-cloud-compute (==0.7.0)
Requires-Dist: importlib-metadata (==4.11.3)
Requires-Dist: protobuf (==3.20.1)
Requires-Dist: click (==8.1.3)
Requires-Dist: opencv-python (==4.5.5.64)
Requires-Dist: google-api-python-client (==1.9.3)
Requires-Dist: google-cloud-tasks (==2.7.1)
Requires-Dist: requests (==2.27.1)
Requires-Dist: numpy (==1.22.3)
Requires-Dist: google-crc32c (==1.3.0)
